milky/__init__.py
milky/async_client.py
milky/bot.py
milky/client.py
milky/models.py
milky_python_sdk-0.4.0.dist-info/METADATA
milky_python_sdk-0.4.0.dist-info/WHEEL
milky_python_sdk-0.4.0.dist-info/licenses/LICENSE
milky_python_sdk-0.4.0.dist-info/RECORD
