Metadata-Version: 2.4
Name: milky-python-sdk
Version: 0.4.0
Summary: Python SDK for Milky Protocol
Project-URL: Repository, https://github.com/notnotype/milky-python-sdk
Author: notnotype
License-File: LICENSE
Classifier: License :: OSI Approved :: MIT License
Classifier: Operating System :: OS Independent
Classifier: Programming Language :: Python :: 3
Requires-Python: >=3.11
Requires-Dist: httpx
Requires-Dist: pydantic
Requires-Dist: python-dotenv
